alerts/__init__.py
alerts/alerts.py
discord_alert/__init__.py
discord_alert/discord_alert.py
tests/__init__.py
tests/test_alerts.py
tests/test_discord_alert.py
DiscordAlerts-0.1.1.dist-info/LICENSE
DiscordAlerts-0.1.1.dist-info/METADATA
DiscordAlerts-0.1.1.dist-info/WHEEL
DiscordAlerts-0.1.1.dist-info/top_level.txt
DiscordAlerts-0.1.1.dist-info/RECORD
