Metadata-Version: 2.1
Name: DiscordAlerts
Version: 0.1.1
Summary: Package for Alerts on Discord
Home-page: https://github.com/gabrielchboff/DiscordAlerts
Author: gabrielchboff
Classifier: Programming Language :: Python :: 3
Classifier: License :: OSI Approved :: MIT License
Classifier: Operating System :: OS Independent
License-File: LICENSE
Requires-Dist: discord-webhook
